{
    "currency": "$",
    "tiers": [
        {
            "name": "Models",
            "description": "3D models made in Blockbench / characters, entities, props, and more.",
            "icon": "&#9632;",
            "prices": [
                { "label": "Basic Model", "detail": "Includes things like blocks, 3D tools, small entities and such.", "price": 15 },
                { "label": "Medium Model", "detail": "Medium sized entites, armor models and such", "price": 25 },
                { "label": "Large Model", "detail": "Large entities, tools. Example : The Ender Dragon", "price": 45 }
            ]
        },
        {
            "name": "Textures",
            "description": "Involves block, item or entity textures. as well as GUIs and etc. (no animations)",
            "icon": "&#9635;",
            "prices": [
                { "label": "16x16", "detail": "includes items, block textures, and icons.", "price": 5 },
                { "label": "32x32", "detail": "if you want more detailed sprites.", "price": 10 },
                { "label": "+64x64", "detail": "involes complicated models and such, can increase price depending on size.", "price": +20 }
            ]
        },
        {
            "name": "Renders",
            "description": "Renders of characters, items, key art, scenery, etc.",
            "icon": "&#10022;",
            "styles": [
                { "image": "images/barebonesrender.png", "label": "Barebones" },
                { "image": "images/cleanrender.png", "label": "Clean" },
                { "image": "images/texturedrender.png", "label": "Textured" }
            ],
            "prices": [
                { "label": "Profile Render", "detail": "single model render.", "price": 10 },
                { "label": "Basic Render", "detail": "basic renders for up to 2 models.", "price": 20 },
                { "label": "Detailed Render", "detail": "varies from keyarts or showcase renders. price can increase depending on the complexity", "price": 40 }
            ]
        }
    ],
    "process": [
        { "step": 1, "title": "Reach Out", "detail": "DM me on Discord with your idea and references." },
        { "step": 2, "title": "Discussion", "detail": "We talk details — scope, style, timeline, and price." },
        { "step": 3, "title": "Mock Up", "detail": "You update me on the designs to reach a final version.." },
        { "step": 4, "title": "Final Design", "detail": "Once everything has been confirmed and reviewed, i work on making the final version." },
        { "step": 5, "title": "Delivery", "detail": "Final files delivered after payment." }
    ],
    "terms": [
        "Prices may vary based on complexity — the listed prices are starting points.",
        "I reserve the right to decline any commission for any reason.",
        "I can only offer discounts if purchases are above 70USD total.",
        "I may use completed work in my portfolio unless agreed otherwise.",
        "No refunds.",
        "Please credit me (AtomicalMoon) if you post the work publicly.",
        "I will not make arkwork that involves in politics or anything controversial. NSFW is fine but will be an additional cost.",
        "if Rush orders are not completed by the estimated time you will not have to pay the extra fee."
    ]
}
